{
  "properties": {
    "api_url": {
      "$ref": "#/$defs/ConfigURLType2"
    },
    "chat": {
      "format": "int64",
      "type": "integer"
    },
    "chat_file": {
      "type": "string"
    },
    "disable_notifications": {
      "type": "boolean"
    },
    "http_config": {
      "$ref": "#/$defs/ConfigHTTPClientConfig"
    },
    "message": {
      "type": "string"
    },
    "message_thread_id": {
      "type": "integer"
    },
    "parse_mode": {
      "type": "string"
    },
    "send_resolved": {
      "type": "boolean"
    },
    "token": {
      "type": "string"
    },
    "token_file": {
      "type": "string"
    }
  },
  "type": "object"
}
